odysee-1.0.2.dist-info/METADATA
odysee-1.0.2.dist-info/WHEEL
odysee-1.0.2.dist-info/licenses/LICENSE
odysee_rust/__init__.py
odysee_rust/odysee_rust.abi3.so
odysee-1.0.2.dist-info/RECORD
