Metadata-Version: 2.4
Name: odysee
Version: 1.0.2
Classifier: Development Status :: 5 - Production/Stable
Classifier: Intended Audience :: Science/Research
Classifier: Intended Audience :: Developers
Classifier: License :: OSI Approved :: MIT License
Classifier: Programming Language :: Python :: 3
Classifier: Programming Language :: Python :: 3.8
Classifier: Programming Language :: Python :: 3.9
Classifier: Programming Language :: Python :: 3.10
Classifier: Programming Language :: Python :: 3.11
Classifier: Programming Language :: Rust
Classifier: Topic :: Scientific/Engineering :: Artificial Intelligence
Classifier: Topic :: Scientific/Engineering :: Information Analysis
Classifier: Topic :: Software Development :: Libraries :: Python Modules
Classifier: Operating System :: OS Independent
Requires-Dist: numpy >=1.24.0
Requires-Dist: torch >=2.0.0
Requires-Dist: transformers >=4.30.0
Requires-Dist: pillow >=10.0.0
Requires-Dist: scipy >=1.10.0
Requires-Dist: pandas >=2.0.0
Requires-Dist: scikit-learn >=1.3.0
Requires-Dist: tqdm >=4.65.0
Requires-Dist: opencv-python >=4.8.0
Requires-Dist: librosa >=0.10.0
Requires-Dist: networkx >=3.1
Requires-Dist: black >=23.0.0 ; extra == 'dev'
Requires-Dist: isort >=5.12.0 ; extra == 'dev'
Requires-Dist: flake8 >=6.0.0 ; extra == 'dev'
Requires-Dist: mypy >=1.0.0 ; extra == 'dev'
Requires-Dist: pytest >=7.0.0 ; extra == 'test'
Requires-Dist: pytest-cov >=4.0.0 ; extra == 'test'
Requires-Dist: pytest-benchmark >=4.0.0 ; extra == 'test'
Requires-Dist: hypothesis >=6.75.3 ; extra == 'test'
Requires-Dist: torch >=2.0.0 ; extra == 'gpu'
Requires-Dist: torchvision >=0.15.0 ; extra == 'gpu'
Requires-Dist: torchaudio >=2.0.0 ; extra == 'gpu'
Requires-Dist: sphinx >=7.0.0 ; extra == 'docs'
Requires-Dist: sphinx-rtd-theme >=1.2.0 ; extra == 'docs'
Requires-Dist: myst-parser >=2.0.0 ; extra == 'docs'
Provides-Extra: dev
Provides-Extra: test
Provides-Extra: gpu
Provides-Extra: docs
License-File: LICENSE
Summary: High-performance quantum-inspired multimodal memory system with adaptive routing and distributed processing capabilities
Keywords: deep-learning,quantum-computing,multimodal,memory-systems,neural-processing,distributed-systems,machine-learning,artificial-intelligence,quantum-inspired,high-performance-computing
Author-email: Aniket Kumar <aniketkumar34@outlook.com>
Maintainer-email: Aniket Kumar <aniketkumar34@outlook.com>
Requires-Python: >=3.8
Project-URL: Homepage, https://github.com/threatthriver/odysee
Project-URL: Repository, https://github.com/threatthriver/odysee
Project-URL: Documentation, https://github.com/threatthriver/odysee/blob/main/README.md
Project-URL: Bug Tracker, https://github.com/threatthriver/odysee/issues
Project-URL: Source Code, https://github.com/threatthriver/odysee
